MANIFEST.in
README
requirements.txt
setup.py
test/test.py
wasanbon/__init__.py
wasanbon.egg-info/PKG-INFO
wasanbon.egg-info/SOURCES.txt
wasanbon.egg-info/dependency_links.txt
wasanbon.egg-info/requires.txt
wasanbon.egg-info/top_level.txt
wasanbon/bin/wasanbon-admin.py
wasanbon/bin/wasanbon-cd.bat
wasanbon/core/__init__.py
wasanbon/core/management/__init__.py
wasanbon/core/management/application.py
wasanbon/core/plugins/__init__.py
wasanbon/core/plugins/admin/binder_plugin/__init__.py
wasanbon/core/plugins/admin/binder_plugin/binder/__init__.py
wasanbon/core/plugins/admin/builder_plugin/__init__.py
wasanbon/core/plugins/admin/eclipse_plugin/__init__.py
wasanbon/core/plugins/admin/editor_plugin/__init__.py
wasanbon/core/plugins/admin/environment_plugin/__init__.py
wasanbon/core/plugins/admin/environment_plugin/settings/repository.yaml
wasanbon/core/plugins/admin/environment_plugin/settings/common/dot.emacs
wasanbon/core/plugins/admin/environment_plugin/settings/common/file.yaml
wasanbon/core/plugins/admin/environment_plugin/settings/common/packages.yaml
wasanbon/core/plugins/admin/environment_plugin/settings/common/path.yaml
wasanbon/core/plugins/admin/environment_plugin/settings/common/repository.yaml
wasanbon/core/plugins/admin/environment_plugin/settings/common/svn.yaml
wasanbon/core/plugins/admin/environment_plugin/settings/debian_x86/apt.yaml
wasanbon/core/plugins/admin/environment_plugin/settings/debian_x86/bashrc
wasanbon/core/plugins/admin/environment_plugin/settings/debian_x86/hints.yaml
wasanbon/core/plugins/admin/environment_plugin/settings/debian_x86/libraries.yaml
wasanbon/core/plugins/admin/environment_plugin/settings/debian_x86/packages.yaml
wasanbon/core/plugins/admin/environment_plugin/settings/debian_x86/path.yaml
wasanbon/core/plugins/admin/environment_plugin/settings/debian_x86/projects.yaml
wasanbon/core/plugins/admin/environment_plugin/settings/debian_x86/repository.yaml
wasanbon/core/plugins/admin/environment_plugin/settings/debian_x86/setting.yaml
wasanbon/core/plugins/admin/environment_plugin/settings/osx/bashrc
wasanbon/core/plugins/admin/environment_plugin/settings/osx/hints.yaml
