Metadata-Version: 1.1
Name: wasanbon
Version: 1.1.0.post5
Summary: Development Framework for Robotics Technology Middleware (RTM)
Home-page: http://www.sugarsweetrobotics.com/
Author: ysuga
Author-email: ysuga@ysuga.net
License: GPLv3
Download-URL: https://github.com/sugarsweetrobotics/wasanbon.git
Platform: UNKNOWN
Classifier: Development Status :: 5 - Production/Stable
Classifier: Environment :: Console
Classifier: Intended Audience :: Developers
Classifier: License :: OSI Approved :: GNU General Public License v3 (GPLv3)
Classifier: Natural Language :: English
Classifier: Operating System :: OS Independent
Classifier: Programming Language :: Python
Classifier: Programming Language :: Python :: 2.7
Classifier: Topic :: Desktop Environment
Classifier: Topic :: Scientific/Engineering
Classifier: Topic :: Software Development :: Libraries :: Application Frameworks
Classifier: Topic :: Software Development
